MANIFEST.in
setup.py
mx_datagen/__init__.py
mx_datagen/company.py
mx_datagen/dates.py
mx_datagen/email.py
mx_datagen/names.py
mx_datagen/phone.py
mx_datagen/postalcode.py
mx_datagen/data_source/CP.json
mx_datagen/data_source/__init__.py
mx_datagen/data_source/address.py
mx_datagen/data_source/company.py
mx_datagen/data_source/emails_data.py
mx_datagen/data_source/ladas.py
mx_datagen/data_source/names.json
mx_datagenerator.egg-info/PKG-INFO
mx_datagenerator.egg-info/SOURCES.txt
mx_datagenerator.egg-info/dependency_links.txt
mx_datagenerator.egg-info/not-zip-safe
mx_datagenerator.egg-info/requires.txt
mx_datagenerator.egg-info/top_level.txt