Metadata-Version: 1.0
Name: mx-datagenerator
Version: 0.4.6.2
Summary: Generador de datos específicamente creado para México
Home-page: https://github.com/ericking97/MX_datagen.git
Author: ericking97
Author-email: ericking97@hotmail.com
License: MIT
Platform: UNKNOWN
